odoo/addons/mail_service_users/LICENSE
odoo/addons/mail_service_users/README.rst
odoo/addons/mail_service_users/__init__.py
odoo/addons/mail_service_users/__manifest__.py
odoo/addons/mail_service_users/i18n/de_CH.po
odoo/addons/mail_service_users/images/screen.png
odoo/addons/mail_service_users/models/__init__.py
odoo/addons/mail_service_users/models/res_config_settings.py
odoo/addons/mail_service_users/models/res_users.py
odoo/addons/mail_service_users/models/update.py
odoo/addons/mail_service_users/static/description/icon.png
odoo/addons/mail_service_users/static/description/index.html
odoo/addons/mail_service_users/views/base.xml
odoo_addon_mail_service_users-18.0.1.0.0.2.dist-info/METADATA
odoo_addon_mail_service_users-18.0.1.0.0.2.dist-info/WHEEL
odoo_addon_mail_service_users-18.0.1.0.0.2.dist-info/top_level.txt
odoo_addon_mail_service_users-18.0.1.0.0.2.dist-info/RECORD
