Metadata-Version: 2.1
Name: odoo-addon-mail_service_users
Version: 18.0.1.0.0.2
Requires-Python: >=3.10
Requires-Dist: odoo==18.0.*
Summary: Exclude service users from warranty contract.
Home-page: https://www.mint-system.ch/
License: AGPL-3
Author: Mint System GmbH
Classifier: Programming Language :: Python
Classifier: Framework :: Odoo
Classifier: Framework :: Odoo :: 18.0
Classifier: License :: OSI Approved :: GNU Affero General Public License v3
